airfly-1.1.0.dist-info/METADATA
airfly-1.1.0.dist-info/WHEEL
airfly-1.1.0.dist-info/entry_points.txt
airfly-1.1.0.dist-info/licenses/LICENSE
airfly/__init__.py
airfly/_meta.py
airfly/_vendor/__init__.py
airfly/_vendor/abc.py
airfly/_vendor/airflow/__init__.py
airfly/_vendor/airflow/decorators/__init__.py
airfly/_vendor/airflow/decorators/base.py
airfly/_vendor/airflow/decorators/bash.py
airfly/_vendor/airflow/decorators/branch_external_python.py
airfly/_vendor/airflow/decorators/branch_python.py
airfly/_vendor/airflow/decorators/branch_virtualenv.py
airfly/_vendor/airflow/decorators/external_python.py
airfly/_vendor/airflow/decorators/python.py
airfly/_vendor/airflow/decorators/python_virtualenv.py
airfly/_vendor/airflow/decorators/sensor.py
airfly/_vendor/airflow/decorators/short_circuit.py
airfly/_vendor/airflow/example_dags/__init__.py
airfly/_vendor/airflow/example_dags/example_dag_decorator.py
airfly/_vendor/airflow/example_dags/example_dynamic_task_mapping_with_no_taskflow_operators.py
airfly/_vendor/airflow/example_dags/example_skip_dag.py
airfly/_vendor/airflow/models/__init__.py
airfly/_vendor/airflow/models/abstractoperator.py
airfly/_vendor/airflow/models/baseoperator.py
airfly/_vendor/airflow/models/skipmixin.py
airfly/_vendor/airflow/models/taskmixin.py
airfly/_vendor/airflow/operators/__init__.py
airfly/_vendor/airflow/operators/bash.py
airfly/_vendor/airflow/operators/branch.py
airfly/_vendor/airflow/operators/datetime.py
airfly/_vendor/airflow/operators/email.py
airfly/_vendor/airflow/operators/empty.py
airfly/_vendor/airflow/operators/generic_transfer.py
airfly/_vendor/airflow/operators/latest_only.py
airfly/_vendor/airflow/operators/python.py
airfly/_vendor/airflow/operators/smooth.py
airfly/_vendor/airflow/operators/subdag.py
airfly/_vendor/airflow/operators/trigger_dagrun.py
airfly/_vendor/airflow/operators/weekday.py
airfly/_vendor/airflow/providers/__init__.py
airfly/_vendor/airflow/providers/airbyte/__init__.py
airfly/_vendor/airflow/providers/airbyte/operators/__init__.py
airfly/_vendor/airflow/providers/airbyte/operators/airbyte.py
airfly-1.1.0.dist-info/RECORD
