Metadata-Version: 2.1
Name: airfly
Version: 1.1.0
Summary: Auto generate Airflow's dag.py on the fly
Author-Email: ryanchao2012 <ryanchao2012@gmail.com>
License: MIT
Classifier: Programming Language :: Python :: 3.8
Classifier: Programming Language :: Python :: 3.9
Classifier: Programming Language :: Python :: 3.10
Classifier: Programming Language :: Python :: 3.11
Classifier: Programming Language :: Python :: 3.12
Requires-Python: >=3.8
Requires-Dist: attrs
Requires-Dist: cattrs
Requires-Dist: regex
Requires-Dist: networkx
Requires-Dist: black
Requires-Dist: isort
Requires-Dist: click
Requires-Dist: libcst
Requires-Dist: asttrs
Requires-Dist: loguru
Provides-Extra: dev
Requires-Dist: ipython>=8.12.3; extra == "dev"
Requires-Dist: pytest>=8.1.1; extra == "dev"
Requires-Dist: invoke>=2.2.0; extra == "dev"
Requires-Dist: pytest-cov>=4.1.0; extra == "dev"
Requires-Dist: gutt>=1.1.0; extra == "dev"
Requires-Dist: toml>=0.10.2; extra == "dev"
Requires-Dist: pytest-mock>=3.14.0; extra == "dev"
